tinyhash.py
tinyhash-0.0.1.dist-info/METADATA
tinyhash-0.0.1.dist-info/WHEEL
tinyhash-0.0.1.dist-info/licenses/LICENSE
tinyhash-0.0.1.dist-info/RECORD
